{"stats":{"minecraft:picked_up":{"minecraft:raw_iron":4,"minecraft:stick":8,"minecraft:crafting_table":7,"minecraft:lilac":11,"minecraft:porkchop":4,"minecraft:oak_log":24,"minecraft:spruce_sapling":9,"minecraft:spruce_log":40,"minecraft:mossy_cobblestone":7,"minecraft:dirt":23,"biomesoplenty:maple_sapling":2,"minecraft:rotten_flesh":2,"minecraft:wheat_seeds":3,"minecraft:spruce_planks":9,"minecraft:oak_planks":10,"minecraft:cobblestone":36},"minecraft:mined":{"minecraft:mossy_cobblestone":7,"minecraft:iron_ore":4,"minecraft:lilac":12,"minecraft:spruce_log":35,"treechop:chopped_log":1,"minecraft:crafting_table":7,"minecraft:grass":8,"minecraft:grass_block":19,"minecraft:oak_log":24,"minecraft:dirt":4,"minecraft:spruce_leaves":1,"biomesoplenty:sprout":12,"minecraft:stone":36,"minecraft:oak_planks":10,"minecraft:fern":1},"minecraft:killed":{"minecraft:zombie":2,"minecraft:pig":2,"minecraft:zombie_villager":1},"minecraft:crafted":{"minecraft:oak_door":3,"minecraft:oak_planks":96,"minecraft:spruce_sign":3,"minecraft:crafting_table":1,"minecraft:spruce_planks":40,"minecraft:stick":16,"minecraft:wooden_pickaxe":1,"minecraft:stone_pickaxe":2,"minecraft:wooden_axe":1,"minecraft:stone_sword":2,"minecraft:chest":2,"minecraft:stone_axe":2},"minecraft:used":{"minecraft:wooden_axe":49,"minecraft:stone_sword":17,"minecraft:stone_pickaxe":40,"minecraft:oak_planks":90,"minecraft:chest":2,"minecraft:wooden_pickaxe":11,"minecraft:spruce_sign":1,"minecraft:lilac":1,"minecraft:oak_door":1,"minecraft:stone_axe":52,"minecraft:mossy_cobblestone":7,"minecraft:dirt":6,"minecraft:crafting_table":7},"minecraft:custom":{"minecraft:time_since_rest":14257,"minecraft:sprint_one_cm":29302,"minecraft:damage_taken":185,"minecraft:walk_one_cm":39904,"minecraft:mob_kills":5,"minecraft:damage_dealt":790,"minecraft:interact_with_crafting_table":9,"minecraft:fly_one_cm":33608,"minecraft:open_chest":3,"minecraft:crouch_one_cm":2423,"minecraft:play_time":14257,"tombstone:undead_killed":3,"minecraft:sneak_time":1119,"minecraft:jump":198,"minecraft:time_since_death":14257,"minecraft:total_world_time":14257,"minecraft:fall_one_cm":6911}},"DataVersion":3465}